baseint/__init__.py
baseint-0.0.8.dist-info/METADATA
baseint-0.0.8.dist-info/WHEEL
baseint-0.0.8.dist-info/top_level.txt
baseint-0.0.8.dist-info/RECORD
