Metadata-Version: 2.4
Name: baseint
Version: 0.0.8
Summary: A Python class for handling integers in arbitrary bases.
Author-email: NumbersTada <tadaktatak61@gmail.com>
Classifier: Programming Language :: Python :: 3
Classifier: Operating System :: OS Independent
Classifier: License :: OSI Approved :: MIT License
Requires-Python: >=3.6
